CHANGELOG.rst
scrap2rst/__init__.py
scrap2rst/cmd.py
scrap2rst/converter.py
scrap2rst/logging.py
scrap2rst-0.3.0.dist-info/entry_points.txt
scrap2rst-0.3.0.dist-info/LICENSE
scrap2rst-0.3.0.dist-info/WHEEL
scrap2rst-0.3.0.dist-info/METADATA
scrap2rst-0.3.0.dist-info/RECORD
