Metadata-Version: 2.1
Name: scrap2rst
Version: 0.3.0
Summary: Converting scrapbox syntax into reStructuredText
Home-page: https://github.com/shimizukawa/scrap2rst
License: MIT
Keywords: markup,scrapbox,reStructuredText,reST
Author: shimizukawa
Author-email: shimizukawa@gmail.com
Requires-Python: >=3.6
Classifier: Development Status :: 3 - Alpha
Classifier: Environment :: Console
Classifier: Intended Audience :: Developers
Classifier: Intended Audience :: Information Technology
Classifier: License :: OSI Approved :: MIT License
Classifier: Operating System :: MacOS :: MacOS X
Classifier: Operating System :: Microsoft :: Windows
Classifier: Operating System :: POSIX :: BSD
Classifier: Operating System :: POSIX :: Linux
Classifier: Operating System :: Unix
Classifier: Programming Language :: Python :: 3
Classifier: Programming Language :: Python :: 3 :: Only
Classifier: Programming Language :: Python :: 3.6
Classifier: Programming Language :: Python :: 3.7
Classifier: Topic :: Text Processing :: Markup
Classifier: Topic :: Utilities
Project-URL: Documentation, https://github.com/shimizukawa/scrap2rst/blob/master/README.rst
Project-URL: Repository, https://github.com/shimizukawa/scrap2rst
